[
  {
    "model": "quick_decisions.quickdecisiontype",
    "pk": 1,
    "fields": {
      "theme": 2,
      "name": "Opheffen last onder dwangsom",
      "workflow_option": "besluit"
    }
  },
  {
    "model": "quick_decisions.quickdecisiontype",
    "pk": 2,
    "fields": {
      "theme": 2,
      "name": "Intrekken bestuurlijke boete",
      "workflow_option": "besluit"
    }
  },
  {
    "model": "quick_decisions.quickdecisiontype",
    "pk": 3,
    "fields": {
      "theme": 3,
      "name": "Opheffen last onder dwangsom",
      "workflow_option": "besluit"
    }
  },
  {
    "model": "quick_decisions.quickdecisiontype",
    "pk": 4,
    "fields": {
      "theme": 3,
      "name": "Intrekken bestuurlijke boete",
      "workflow_option": "besluit"
    }
  },
  {
    "model": "quick_decisions.quickdecisiontype",
    "pk": 5,
    "fields": {
      "theme": 4,
      "name": "Opheffen last onder dwangsom",
      "workflow_option": "besluit"
    }
  },
  {
    "model": "quick_decisions.quickdecisiontype",
    "pk": 6,
    "fields": {
      "theme": 4,
      "name": "Intrekken bestuurlijke boete",
      "workflow_option": "besluit"
    }
  },
  {
    "model": "quick_decisions.quickdecisiontype",
    "pk": 7,
    "fields": {
      "theme": 5,
      "name": "Opheffen last onder dwangsom",
      "workflow_option": "besluit"
    }
  },
  {
    "model": "quick_decisions.quickdecisiontype",
    "pk": 8,
    "fields": {
      "theme": 5,
      "name": "Intrekken bestuurlijke boete",
      "workflow_option": "besluit"
    }
  },
  {
    "model": "quick_decisions.quickdecisiontype",
    "pk": 9,
    "fields": {
      "theme": 6,
      "name": "Opheffen last onder dwangsom",
      "workflow_option": "besluit"
    }
  },
  {
    "model": "quick_decisions.quickdecisiontype",
    "pk": 10,
    "fields": {
      "theme": 6,
      "name": "Intrekken bestuurlijke boete",
      "workflow_option": "besluit"
    }
  },
  {
    "model": "quick_decisions.quickdecisiontype",
    "pk": 11,
    "fields": {
      "theme": 7,
      "name": "Opheffen last onder dwangsom",
      "workflow_option": "besluit"
    }
  },
  {
    "model": "quick_decisions.quickdecisiontype",
    "pk": 12,
    "fields": {
      "theme": 7,
      "name": "Intrekken bestuurlijke boete",
      "workflow_option": "besluit"
    }
  }
]
